pyg_cell/__init__.py
pyg_cell/_acell.py
pyg_cell/_cache.py
pyg_cell/_cell.py
pyg_cell/_cell_runner.py
pyg_cell/_dag.py
pyg_cell/_db_cell.py
pyg_cell/_latest_cell.py
pyg_cell/_periodic_cell.py
pyg_cell/_tree.py
pyg_cell/_types.py
pyg_cell/app.py
pyg_cell-0.0.50.dist-info/licenses/LICENSE.txt
pyg_cell-0.0.50.dist-info/METADATA
pyg_cell-0.0.50.dist-info/WHEEL
pyg_cell-0.0.50.dist-info/top_level.txt
pyg_cell-0.0.50.dist-info/RECORD
