Metadata-Version: 2.4
Name: pyg-cell
Version: 0.0.50
Summary: Utilities for data manipulation including creation of DAGs and tables
Home-page: https://github.com/gityoav/pyg-cell
Author: Yoav Git
Author-email: yoav.git@gmail.com
Project-URL: Bug Tracker, https://github.com/gityoav/pyg-cell/issues
Classifier: Programming Language :: Python :: 3
Classifier: License :: OSI Approved :: GNU General Public License v3 (GPLv3)
Classifier: Operating System :: OS Independent
Requires-Python: >=3.6
License-File: LICENSE.txt
Requires-Dist: pyg-base
Requires-Dist: pyg-encoders
Dynamic: license-file
